ezhashlib/__init__.py
ezhashlib-1.1.0.dist-info/METADATA
ezhashlib-1.1.0.dist-info/WHEEL
ezhashlib-1.1.0.dist-info/top_level.txt
ezhashlib-1.1.0.dist-info/RECORD
