Metadata-Version: 2.1
Name: ezhashlib
Version: 1.1.0
Summary: Convenience wrapper around the hashlib library
Home-page: https://github.com/joshm12345/ezhashlib
Author: Josh Morrow
Author-email: joshmorrow12@icloud.com
License: MIT
Platform: UNKNOWN
